sc_data/__init__.py
sc_data/constants.py
sc_data/data.py
sc_data/data/db_hash
sc_data/data/sc-data-priceless.db
sc_data/data/sc-data-priceless.hash
sparecores_data-0.3.4.dist-info/licenses/LICENSE
sparecores_data-0.3.4.dist-info/METADATA
sparecores_data-0.3.4.dist-info/WHEEL
sparecores_data-0.3.4.dist-info/top_level.txt
sparecores_data-0.3.4.dist-info/RECORD
