Metadata-Version: 2.4
Name: sparecores-data
Version: 0.3.4
Summary: Structured data on cloud servers collected by sparecores-crawler.
Author: Gergely Daroczi, Attila Nagy
Maintainer-email: Spare Cores team <pkg@sparecores.com>
Project-URL: repository, https://github.com/SpareCores/sc-data
Project-URL: issues, https://github.com/SpareCores/sc-data/issues
Project-URL: homepage, https://sparecores.com
Keywords: cloud,compute,etl,sqlite,spot-instances,cost-optimization
Classifier: Programming Language :: Python :: 3
Classifier: Operating System :: OS Independent
Classifier: Development Status :: 5 - Production/Stable
Requires-Python: >=3.8
License-File: LICENSE
Requires-Dist: requests
Provides-Extra: testing
Requires-Dist: pytest; extra == "testing"
Requires-Dist: sqlalchemy; extra == "testing"
Provides-Extra: all
Requires-Dist: sparecores-data[testing]; extra == "all"
Dynamic: license-file
